KoEngMapper/KoEngMapper.py
KoEngMapper/__init__.py
gksdudaovld/KoEngMapper.py
gksdudaovld/__init__.py
gksdudaovld-1.0.5.dist-info/METADATA
gksdudaovld-1.0.5.dist-info/WHEEL
gksdudaovld-1.0.5.dist-info/top_level.txt
gksdudaovld-1.0.5.dist-info/RECORD
