Metadata-Version: 2.1
Name: gksdudaovld
Version: 1.0.5
Summary: Mapping module for conversion between Korean and English
Home-page: https://github.com/ForestHouse2316/gksdudaovld
Author: ForestHouse
Author-email: foresthouse2316@gmail.com
License: MIT
Platform: UNKNOWN
Requires-Python: >=3
